aiohttp_client_cache/__init__.py
aiohttp_client_cache/cache_control.py
aiohttp_client_cache/cache_keys.py
aiohttp_client_cache/py.typed
aiohttp_client_cache/response.py
aiohttp_client_cache/session.py
aiohttp_client_cache/signatures.py
aiohttp_client_cache/backends/__init__.py
aiohttp_client_cache/backends/base.py
aiohttp_client_cache/backends/dynamodb.py
aiohttp_client_cache/backends/filesystem.py
aiohttp_client_cache/backends/mongodb.py
aiohttp_client_cache/backends/redis.py
aiohttp_client_cache/backends/sqlite.py
aiohttp_client_cache-0.14.3.dist-info/METADATA
aiohttp_client_cache-0.14.3.dist-info/WHEEL
aiohttp_client_cache-0.14.3.dist-info/licenses/LICENSE
aiohttp_client_cache-0.14.3.dist-info/RECORD
