Metadata-Version: 2.4
Name: aiohttp-client-cache
Version: 0.14.3
Summary: Persistent cache for aiohttp requests
Project-URL: Homepage, https://github.com/requests-cache/aiohttp-client-cache
Project-URL: Repository, https://github.com/requests-cache/aiohttp-client-cache
Project-URL: Documentation, https://aiohttp-client-cache.readthedocs.io
Author: Jordan Cook, Alessio Locatelli
License: MIT License
License-File: LICENSE
Keywords: aiohttp,async,asyncio,cache,cache-backends,client,dragonflydb,dynamodb,http,mongodb,persistence,redis,requests,sqlite
Classifier: Development Status :: 4 - Beta
Classifier: Framework :: AsyncIO
Classifier: Framework :: aiohttp
Classifier: Intended Audience :: Developers
Classifier: Topic :: Software Development :: Libraries :: Python Modules
Classifier: Typing :: Typed
Requires-Python: >=3.9
Requires-Dist: aiohttp>=3.8
Requires-Dist: attrs>=21.2
Requires-Dist: itsdangerous>=2.0
Requires-Dist: typing-extensions>=4; python_version <= '3.10'
Requires-Dist: url-normalize>=2.2
Provides-Extra: all
Requires-Dist: aioboto3>=9.0; extra == 'all'
Requires-Dist: aiobotocore>=2.0; extra == 'all'
Requires-Dist: aiofiles>=0.6.0; extra == 'all'
Requires-Dist: aiosqlite>=0.20; extra == 'all'
Requires-Dist: motor>=3.1; extra == 'all'
Requires-Dist: redis>=4.2; extra == 'all'
Provides-Extra: dynamodb
Requires-Dist: aioboto3>=9.0; extra == 'dynamodb'
Requires-Dist: aiobotocore>=2.0; extra == 'dynamodb'
Provides-Extra: filesystem
Requires-Dist: aiofiles>=0.6.0; extra == 'filesystem'
Requires-Dist: aiosqlite>=0.20; extra == 'filesystem'
Provides-Extra: mongodb
Requires-Dist: motor>=3.1; extra == 'mongodb'
Provides-Extra: redis
Requires-Dist: redis>=4.2; extra == 'redis'
Provides-Extra: sqlite
Requires-Dist: aiosqlite>=0.20; extra == 'sqlite'
